api_client_poc/__init__.py
api_client_poc/client.py
api_client_poc-0.0.1.dist-info/METADATA
api_client_poc-0.0.1.dist-info/WHEEL
api_client_poc-0.0.1.dist-info/top_level.txt
api_client_poc-0.0.1.dist-info/RECORD
